Metadata-Version: 2.1
Name: melkdb
Version: 0.2.0
Summary: MelkDB: A faster key-value database
Home-page: https://github.com/jaedsonpys/melkdb
Author: Jaedson Silva
Author-email: jaedson.dev@proton.me
License: MIT License
Project-URL: License, https://github.com/jaedsonpys/melkdb/blob/master/LICENSE
Project-URL: Documentation, https://github.com/jaedsonpys/melkdb/tree/master/docs
Keywords: database,noSQL,key-value,db,engine
Platform: UNKNOWN
Classifier: License :: OSI Approved :: MIT License
Classifier: Development Status :: 5 - Production/Stable
Classifier: Intended Audience :: Developers
Classifier: Intended Audience :: System Administrators
Classifier: Intended Audience :: Science/Research
Classifier: Natural Language :: English
Classifier: Operating System :: OS Independent
Classifier: Programming Language :: Python :: 3
Classifier: Topic :: Database :: Database Engines/Servers
License-File: LICENSE
